[
  {
    "courseName": {
      "name": "Kiến Thức Nhập Môn IT 7",
      "date": "2023-10-18",
      "content": "Course content for Kiến Thức Nhập Môn IT 2."
    },
    "fee": "500.000VND",
    "discountfee": "299.000VND",
    "trailer": "src/assets/img/z4778395317768_221677d2d7c20790522f11ec8d23c344.jpg"
  },
  {
    "courseName": {
      "name": "Kiến Thức Nhập Môn IT 7",
      "date": "2023-10-18",
      "content": "Course content for Kiến Thức Nhập Môn IT 2."
    },
    "fee": "500.000VND",
    "discountfee": "299.000VND",
    "trailer": "src/assets/img/z4778395331877_f7d671cc721b6eaecbd4c7967e5c0fa6.jpg"
  },
  {
    "courseName": {
      "name": "Kiến Thức Nhập Môn IT 7",
      "date": "2023-10-18",
      "content": "Course content for Kiến Thức Nhập Môn IT 2."
    },
    "fee": "500.000VND",
    "discountfee": "299.000VND",
    "trailer": "src/assets/img/z4778395343965_f9b55b357ac6b3de90e74bac73d10923.jpg"
  },
  {
    "courseName": {
      "name": "Kiến Thức Nhập Môn IT 7",
      "date": "2023-10-18",
      "content": "Course content for Kiến Thức Nhập Môn IT 2."
    },
    "fee": "500.000VND",
    "discountfee": "299.000VND",
    "trailer": "src/assets/img/z4778395343964_9f9e578a96f51f311e2c50a53bf6bba2.jpg"
  },
  {
    "courseName": {
      "name": "Kiến Thức Nhập Môn IT 7",
      "date": "2023-10-18",
      "content": "Course content for Kiến Thức Nhập Môn IT 2."
    },
    "fee": "500.000VND",
    "discountfee": "299.000VND",
    "trailer": "src/assets/img/z4778395343964_9f9e578a96f51f311e2c50a53bf6bba2.jpg"
  }
]
